{
  "id": "689-640-S--2020-05-05--13.30.50--detections",
  "model": "ResNet50_COCO_best_v2.0.1.h5",
  "summary": {
    "total": 5,
    "car": 3,
    "person": 2
  },
  "689-640-S--2020-05-05--13.30.50--detections--1--car--75.3--15x11--133.101v148.112": {
    "type": "car",
    "id": "689-640-S--2020-05-05--13.30.50--detections--1--car--75.3--15x11--133.101v148.112",
    "percentage_probability": 75.33305883407593,
    "box_points": [
      133,
      101,
      148,
      112
    ]
  },
  "689-640-S--2020-05-05--13.30.50--detections--2--car--46.7--10x12--95.134v105.146": {
    "type": "car",
    "id": "689-640-S--2020-05-05--13.30.50--detections--2--car--46.7--10x12--95.134v105.146",
    "percentage_probability": 46.747979521751404,
    "box_points": [
      95,
      134,
      105,
      146
    ]
  },
  "689-640-S--2020-05-05--13.30.50--detections--3--car--76.6--10x13--81.143v91.156": {
    "type": "car",
    "id": "689-640-S--2020-05-05--13.30.50--detections--3--car--76.6--10x13--81.143v91.156",
    "percentage_probability": 76.55489444732666,
    "box_points": [
      81,
      143,
      91,
      156
    ]
  },
  "689-640-S--2020-05-05--13.30.50--detections--4--person--31.9--5x15--51.161v56.176": {
    "type": "person",
    "id": "689-640-S--2020-05-05--13.30.50--detections--4--person--31.9--5x15--51.161v56.176",
    "percentage_probability": 31.863227486610413,
    "box_points": [
      51,
      161,
      56,
      176
    ]
  },
  "689-640-S--2020-05-05--13.30.50--detections--5--person--66.4--6x18--37.208v43.226": {
    "type": "person",
    "id": "689-640-S--2020-05-05--13.30.50--detections--5--person--66.4--6x18--37.208v43.226",
    "percentage_probability": 66.38103127479553,
    "box_points": [
      37,
      208,
      43,
      226
    ]
  }
}
