{
  "id": "689-640-S--2020-05-05--13.20.31--detections",
  "model": "ResNet50_COCO_best_v2.0.1.h5",
  "summary": {
    "total": 5,
    "car": 4,
    "bus": 1
  },
  "689-640-S--2020-05-05--13.20.31--detections--1--car--36.3--14x18--107.88v121.106": {
    "type": "car",
    "id": "689-640-S--2020-05-05--13.20.31--detections--1--car--36.3--14x18--107.88v121.106",
    "percentage_probability": 36.25028729438782,
    "box_points": [
      107,
      88,
      121,
      106
    ]
  },
  "689-640-S--2020-05-05--13.20.31--detections--2--car--38.4--11x13--95.134v106.147": {
    "type": "car",
    "id": "689-640-S--2020-05-05--13.20.31--detections--2--car--38.4--11x13--95.134v106.147",
    "percentage_probability": 38.372308015823364,
    "box_points": [
      95,
      134,
      106,
      147
    ]
  },
  "689-640-S--2020-05-05--13.20.31--detections--3--bus--62.2--14x18--107.88v121.106": {
    "type": "bus",
    "id": "689-640-S--2020-05-05--13.20.31--detections--3--bus--62.2--14x18--107.88v121.106",
    "percentage_probability": 62.213027477264404,
    "box_points": [
      107,
      88,
      121,
      106
    ]
  },
  "689-640-S--2020-05-05--13.20.31--detections--4--car--90.3--24x19--144.115v168.134": {
    "type": "car",
    "id": "689-640-S--2020-05-05--13.20.31--detections--4--car--90.3--24x19--144.115v168.134",
    "percentage_probability": 90.26539325714111,
    "box_points": [
      144,
      115,
      168,
      134
    ]
  },
  "689-640-S--2020-05-05--13.20.31--detections--5--car--70.8--46x28--305.143v351.171": {
    "type": "car",
    "id": "689-640-S--2020-05-05--13.20.31--detections--5--car--70.8--46x28--305.143v351.171",
    "percentage_probability": 70.81736326217651,
    "box_points": [
      305,
      143,
      351,
      171
    ]
  }
}
