{
  "id": "689-640-S--2020-05-05--13.28.38--detections",
  "model": "ResNet50_COCO_best_v2.0.1.h5",
  "summary": {
    "total": 10,
    "car": 9,
    "person": 1
  },
  "689-640-S--2020-05-05--13.28.38--detections--1--car--41.5--8x8--100.87v108.95": {
    "type": "car",
    "id": "689-640-S--2020-05-05--13.28.38--detections--1--car--41.5--8x8--100.87v108.95",
    "percentage_probability": 41.46009683609009,
    "box_points": [
      100,
      87,
      108,
      95
    ]
  },
  "689-640-S--2020-05-05--13.28.38--detections--2--car--55.1--14x9--151.96v165.105": {
    "type": "car",
    "id": "689-640-S--2020-05-05--13.28.38--detections--2--car--55.1--14x9--151.96v165.105",
    "percentage_probability": 55.08020520210266,
    "box_points": [
      151,
      96,
      165,
      105
    ]
  },
  "689-640-S--2020-05-05--13.28.38--detections--3--car--29.7--12x10--182.99v194.109": {
    "type": "car",
    "id": "689-640-S--2020-05-05--13.28.38--detections--3--car--29.7--12x10--182.99v194.109",
    "percentage_probability": 29.675740003585815,
    "box_points": [
      182,
      99,
      194,
      109
    ]
  },
  "689-640-S--2020-05-05--13.28.38--detections--4--car--62.8--16x11--184.99v200.110": {
    "type": "car",
    "id": "689-640-S--2020-05-05--13.28.38--detections--4--car--62.8--16x11--184.99v200.110",
    "percentage_probability": 62.76218891143799,
    "box_points": [
      184,
      99,
      200,
      110
    ]
  },
  "689-640-S--2020-05-05--13.28.38--detections--5--car--66.7--13x11--190.97v203.108": {
    "type": "car",
    "id": "689-640-S--2020-05-05--13.28.38--detections--5--car--66.7--13x11--190.97v203.108",
    "percentage_probability": 66.68293476104736,
    "box_points": [
      190,
      97,
      203,
      108
    ]
  },
  "689-640-S--2020-05-05--13.28.38--detections--6--car--84.3--23x15--197.110v220.125": {
    "type": "car",
    "id": "689-640-S--2020-05-05--13.28.38--detections--6--car--84.3--23x15--197.110v220.125",
    "percentage_probability": 84.30061340332031,
    "box_points": [
      197,
      110,
      220,
      125
    ]
  },
  "689-640-S--2020-05-05--13.28.38--detections--7--car--55.2--10x12--95.134v105.146": {
    "type": "car",
    "id": "689-640-S--2020-05-05--13.28.38--detections--7--car--55.2--10x12--95.134v105.146",
    "percentage_probability": 55.1544189453125,
    "box_points": [
      95,
      134,
      105,
      146
    ]
  },
  "689-640-S--2020-05-05--13.28.38--detections--8--person--37.5--9x16--45.173v54.189": {
    "type": "person",
    "id": "689-640-S--2020-05-05--13.28.38--detections--8--person--37.5--9x16--45.173v54.189",
    "percentage_probability": 37.47608661651611,
    "box_points": [
      45,
      173,
      54,
      189
    ]
  },
  "689-640-S--2020-05-05--13.28.38--detections--9--car--53.8--31x19--240.106v271.125": {
    "type": "car",
    "id": "689-640-S--2020-05-05--13.28.38--detections--9--car--53.8--31x19--240.106v271.125",
    "percentage_probability": 53.76830697059631,
    "box_points": [
      240,
      106,
      271,
      125
    ]
  },
  "689-640-S--2020-05-05--13.28.38--detections--10--car--98.5--44x24--291.122v335.146": {
    "type": "car",
    "id": "689-640-S--2020-05-05--13.28.38--detections--10--car--98.5--44x24--291.122v335.146",
    "percentage_probability": 98.47835302352905,
    "box_points": [
      291,
      122,
      335,
      146
    ]
  }
}
