{
  "id": "689-640-S--2020-05-05--13.37.15--detections",
  "model": "ResNet50_COCO_best_v2.0.1.h5",
  "summary": {
    "total": 5,
    "car": 5
  },
  "689-640-S--2020-05-05--13.37.15--detections--1--car--30.4--9x7--77.111v86.118": {
    "type": "car",
    "id": "689-640-S--2020-05-05--13.37.15--detections--1--car--30.4--9x7--77.111v86.118",
    "percentage_probability": 30.442476272583008,
    "box_points": [
      77,
      111,
      86,
      118
    ]
  },
  "689-640-S--2020-05-05--13.37.15--detections--2--car--30.2--16x12--334.129v350.141": {
    "type": "car",
    "id": "689-640-S--2020-05-05--13.37.15--detections--2--car--30.2--16x12--334.129v350.141",
    "percentage_probability": 30.186408758163452,
    "box_points": [
      334,
      129,
      350,
      141
    ]
  },
  "689-640-S--2020-05-05--13.37.15--detections--3--car--97.2--31x18--250.118v281.136": {
    "type": "car",
    "id": "689-640-S--2020-05-05--13.37.15--detections--3--car--97.2--31x18--250.118v281.136",
    "percentage_probability": 97.24228382110596,
    "box_points": [
      250,
      118,
      281,
      136
    ]
  },
  "689-640-S--2020-05-05--13.37.15--detections--4--car--92.3--45x19--305.126v350.145": {
    "type": "car",
    "id": "689-640-S--2020-05-05--13.37.15--detections--4--car--92.3--45x19--305.126v350.145",
    "percentage_probability": 92.25757122039795,
    "box_points": [
      305,
      126,
      350,
      145
    ]
  },
  "689-640-S--2020-05-05--13.37.15--detections--5--car--88.0--45x32--307.147v352.179": {
    "type": "car",
    "id": "689-640-S--2020-05-05--13.37.15--detections--5--car--88.0--45x32--307.147v352.179",
    "percentage_probability": 87.95604109764099,
    "box_points": [
      307,
      147,
      352,
      179
    ]
  }
}
