{
  "id": "689-640-S--2020-05-05--13.16.31--detections",
  "model": "ResNet50_COCO_best_v2.0.1.h5",
  "summary": {
    "total": 5,
    "car": 4,
    "person": 1
  },
  "689-640-S--2020-05-05--13.16.31--detections--1--car--25.2--10x8--54.95v64.103": {
    "type": "car",
    "id": "689-640-S--2020-05-05--13.16.31--detections--1--car--25.2--10x8--54.95v64.103",
    "percentage_probability": 25.154387950897217,
    "box_points": [
      54,
      95,
      64,
      103
    ]
  },
  "689-640-S--2020-05-05--13.16.31--detections--2--car--80.0--17x12--170.100v187.112": {
    "type": "car",
    "id": "689-640-S--2020-05-05--13.16.31--detections--2--car--80.0--17x12--170.100v187.112",
    "percentage_probability": 80.02635836601257,
    "box_points": [
      170,
      100,
      187,
      112
    ]
  },
  "689-640-S--2020-05-05--13.16.31--detections--3--car--51.5--12x13--94.134v106.147": {
    "type": "car",
    "id": "689-640-S--2020-05-05--13.16.31--detections--3--car--51.5--12x13--94.134v106.147",
    "percentage_probability": 51.52777433395386,
    "box_points": [
      94,
      134,
      106,
      147
    ]
  },
  "689-640-S--2020-05-05--13.16.31--detections--4--person--30.2--5x19--51.185v56.204": {
    "type": "person",
    "id": "689-640-S--2020-05-05--13.16.31--detections--4--person--30.2--5x19--51.185v56.204",
    "percentage_probability": 30.190753936767578,
    "box_points": [
      51,
      185,
      56,
      204
    ]
  },
  "689-640-S--2020-05-05--13.16.31--detections--5--car--93.6--29x22--173.118v202.140": {
    "type": "car",
    "id": "689-640-S--2020-05-05--13.16.31--detections--5--car--93.6--29x22--173.118v202.140",
    "percentage_probability": 93.61100792884827,
    "box_points": [
      173,
      118,
      202,
      140
    ]
  }
}
