{
  "id": "689-640-S--2020-05-05--13.57.52--detections",
  "model": "ResNet50_COCO_best_v2.0.1.h5",
  "summary": {
    "total": 11,
    "car": 7,
    "person": 4
  },
  "689-640-S--2020-05-05--13.57.52--detections--1--car--34.9--9x10--91.90v100.100": {
    "type": "car",
    "id": "689-640-S--2020-05-05--13.57.52--detections--1--car--34.9--9x10--91.90v100.100",
    "percentage_probability": 34.85875129699707,
    "box_points": [
      91,
      90,
      100,
      100
    ]
  },
  "689-640-S--2020-05-05--13.57.52--detections--2--car--35.2--10x10--107.92v117.102": {
    "type": "car",
    "id": "689-640-S--2020-05-05--13.57.52--detections--2--car--35.2--10x10--107.92v117.102",
    "percentage_probability": 35.152557492256165,
    "box_points": [
      107,
      92,
      117,
      102
    ]
  },
  "689-640-S--2020-05-05--13.57.52--detections--3--car--38.7--11x12--125.93v136.105": {
    "type": "car",
    "id": "689-640-S--2020-05-05--13.57.52--detections--3--car--38.7--11x12--125.93v136.105",
    "percentage_probability": 38.724371790885925,
    "box_points": [
      125,
      93,
      136,
      105
    ]
  },
  "689-640-S--2020-05-05--13.57.52--detections--4--car--77.0--19x18--118.110v137.128": {
    "type": "car",
    "id": "689-640-S--2020-05-05--13.57.52--detections--4--car--77.0--19x18--118.110v137.128",
    "percentage_probability": 76.9517183303833,
    "box_points": [
      118,
      110,
      137,
      128
    ]
  },
  "689-640-S--2020-05-05--13.57.52--detections--5--person--35.4--7x24--31.195v38.219": {
    "type": "person",
    "id": "689-640-S--2020-05-05--13.57.52--detections--5--person--35.4--7x24--31.195v38.219",
    "percentage_probability": 35.381948947906494,
    "box_points": [
      31,
      195,
      38,
      219
    ]
  },
  "689-640-S--2020-05-05--13.57.52--detections--6--person--55.9--7x21--41.204v48.225": {
    "type": "person",
    "id": "689-640-S--2020-05-05--13.57.52--detections--6--person--55.9--7x21--41.204v48.225",
    "percentage_probability": 55.86971044540405,
    "box_points": [
      41,
      204,
      48,
      225
    ]
  },
  "689-640-S--2020-05-05--13.57.52--detections--7--person--25.4--9x18--37.207v46.225": {
    "type": "person",
    "id": "689-640-S--2020-05-05--13.57.52--detections--7--person--25.4--9x18--37.207v46.225",
    "percentage_probability": 25.388693809509277,
    "box_points": [
      37,
      207,
      46,
      225
    ]
  },
  "689-640-S--2020-05-05--13.57.52--detections--8--person--69.5--7x19--55.208v62.227": {
    "type": "person",
    "id": "689-640-S--2020-05-05--13.57.52--detections--8--person--69.5--7x19--55.208v62.227",
    "percentage_probability": 69.46854591369629,
    "box_points": [
      55,
      208,
      62,
      227
    ]
  },
  "689-640-S--2020-05-05--13.57.52--detections--9--car--78.1--20x15--173.100v193.115": {
    "type": "car",
    "id": "689-640-S--2020-05-05--13.57.52--detections--9--car--78.1--20x15--173.100v193.115",
    "percentage_probability": 78.10419797897339,
    "box_points": [
      173,
      100,
      193,
      115
    ]
  },
  "689-640-S--2020-05-05--13.57.52--detections--10--car--55.9--51x33--282.118v333.151": {
    "type": "car",
    "id": "689-640-S--2020-05-05--13.57.52--detections--10--car--55.9--51x33--282.118v333.151",
    "percentage_probability": 55.926185846328735,
    "box_points": [
      282,
      118,
      333,
      151
    ]
  },
  "689-640-S--2020-05-05--13.57.52--detections--11--car--98.6--62x57--194.162v256.219": {
    "type": "car",
    "id": "689-640-S--2020-05-05--13.57.52--detections--11--car--98.6--62x57--194.162v256.219",
    "percentage_probability": 98.63172769546509,
    "box_points": [
      194,
      162,
      256,
      219
    ]
  }
}
