{
  "id": "689-640-S--2020-05-05--13.18.46--detections",
  "model": "ResNet50_COCO_best_v2.0.1.h5",
  "summary": {
    "total": 5,
    "car": 5
  },
  "689-640-S--2020-05-05--13.18.46--detections--1--car--77.4--14x12--117.99v131.111": {
    "type": "car",
    "id": "689-640-S--2020-05-05--13.18.46--detections--1--car--77.4--14x12--117.99v131.111",
    "percentage_probability": 77.36340761184692,
    "box_points": [
      117,
      99,
      131,
      111
    ]
  },
  "689-640-S--2020-05-05--13.18.46--detections--2--car--57.1--17x12--164.99v181.111": {
    "type": "car",
    "id": "689-640-S--2020-05-05--13.18.46--detections--2--car--57.1--17x12--164.99v181.111",
    "percentage_probability": 57.086265087127686,
    "box_points": [
      164,
      99,
      181,
      111
    ]
  },
  "689-640-S--2020-05-05--13.18.46--detections--3--car--70.9--26x16--220.110v246.126": {
    "type": "car",
    "id": "689-640-S--2020-05-05--13.18.46--detections--3--car--70.9--26x16--220.110v246.126",
    "percentage_probability": 70.86367011070251,
    "box_points": [
      220,
      110,
      246,
      126
    ]
  },
  "689-640-S--2020-05-05--13.18.46--detections--4--car--87.5--29x21--177.118v206.139": {
    "type": "car",
    "id": "689-640-S--2020-05-05--13.18.46--detections--4--car--87.5--29x21--177.118v206.139",
    "percentage_probability": 87.4859869480133,
    "box_points": [
      177,
      118,
      206,
      139
    ]
  },
  "689-640-S--2020-05-05--13.18.46--detections--5--car--96.1--45x27--255.126v300.153": {
    "type": "car",
    "id": "689-640-S--2020-05-05--13.18.46--detections--5--car--96.1--45x27--255.126v300.153",
    "percentage_probability": 96.05247974395752,
    "box_points": [
      255,
      126,
      300,
      153
    ]
  }
}
